Metadata-Version: 2.1
Name: jk-trioinput
Version: 0.2019.10.10
Summary: This python module provides asynchroneous console input.
Home-page: https://github.com/jkpubsrc/python-module-jk-trioinput
Author: Jürgen Knauth
Author-email: pubsrc@binary-overflow.de
License: Apache 2.0
Download-URL: https://github.com/jkpubsrc/python-module-jk-trioinput/tarball/0.2019.10.10
Keywords: ...
Platform: UNKNOWN
Classifier: Development Status :: 3 - Alpha
Classifier: License :: OSI Approved :: Apache Software License
